{"DEPUTADO ESTADUAL": {"TOTAL_RJ": 9572486, "CIDADES": {"DUAS BARRAS": {"total_validos": 7211, "candidatos": [{"nome": "PEDRO ROGERIO VIEIRA CABRAL", "numero": "40233", "votos": 1033, "sq_candidato": "190000000806", "posicao": 1}, {"nome": "#NULO#", "numero": "22", "votos": 664, "sq_candidato": null, "posicao": 2}, {"nome": "ALTINEU CORTES FREITAS COUTINHO", "numero": "22369", "votos": 648, "sq_candidato": "190000003956", "posicao": 3}, {"nome": "PAULO CÉSAR MELO DE SÁ", "numero": "15288", "votos": 582, "sq_candidato": "190000002745", "posicao": 4}, {"nome": "ANDRE GUSTAVO PEREIRA CORREA DA SILVA", "numero": "23123", "votos": 373, "sq_candidato": "190000001250", "posicao": 5}, {"nome": "VOTO BRANCO", "numero": "95", "votos": 363, "sq_candidato": null, "posicao": 6}, {"nome": "RAFAEL CARNEIRO MONTEIRO PICCIANI", "numero": "15159", "votos": 320, "sq_candidato": "190000002749", "posicao": 7}, {"nome": "MARCOS ABRAHAO", "numero": "70123", "votos": 311, "sq_candidato": "190000002327", "posicao": 8}, {"nome": "VOTO NULO", "numero": "96", "votos": 278, "sq_candidato": null, "posicao": 9}, {"nome": "AYRTHON CARLOS MAIATTO DIAS", "numero": "11003", "votos": 250, "sq_candidato": "190000000053", "posicao": 10}, {"nome": "LUCIANO CAMPOS FARIA", "numero": "12612", "votos": 250, "sq_candidato": "190000003881", "posicao": 11}, {"nome": "ALCEBIADES SABINO DOS SANTOS", "numero": "20120", "votos": 198, "sq_candidato": "190000001987", "posicao": 12}, {"nome": "LUIZ ANTONIO MARTINS", "numero": "12200", "votos": 154, "sq_candidato": "190000000945", "posicao": 13}, {"nome": "MAURICIO NACIF HABIB", "numero": "65666", "votos": 127, "sq_candidato": "190000003456", "posicao": 14}, {"nome": "GUSTAVO REIS FERREIRA", "numero": "40212", "votos": 119, "sq_candidato": "190000000763", "posicao": 15}, {"nome": "CHRISTINO ÁUREO DA SILVA", "numero": "33233", "votos": 118, "sq_candidato": "190000000748", "posicao": 16}, {"nome": "MARIA DAS GRAÇAS TUZE DE MATOS", "numero": "15122", "votos": 114, "sq_candidato": "190000002729", "posicao": 17}, {"nome": "HELIO GONÇALVES CORREA", "numero": "20200", "votos": 99, "sq_candidato": "190000002016", "posicao": 18}, {"nome": "SAMUEL LIMA MALAFAIA", "numero": "22777", "votos": 70, "sq_candidato": "190000004041", "posicao": 19}, {"nome": "MARCOS DA SILVA ALBERTO MEDEIROS", "numero": "14000", "votos": 62, "sq_candidato": "190000003798", "posicao": 20}, {"nome": "MARCIO HENRIQUE CRUZ PACHECO", "numero": "20010", "votos": 61, "sq_candidato": "190000002046", "posicao": 21}, {"nome": "SERAFIM JOAO CARLOS RODRIGUES DE OLIVERIA", "numero": "12678", "votos": 51, "sq_candidato": "190000000980", "posicao": 22}, {"nome": "MARCELO RIBEIRO FREIXO", "numero": "50123", "votos": 47, "sq_candidato": "190000002196", "posicao": 23}, {"nome": "EDINO FIALHO FONSECA", "numero": "22123", "votos": 46, "sq_candidato": "190000003974", "posicao": 24}, {"nome": "WAGNER MONTES DOS SANTOS", "numero": "12123", "votos": 39, "sq_candidato": "190000000988", "posicao": 25}, {"nome": "NILTON WILSON SALOMÃO", "numero": "13104", "votos": 38, "sq_candidato": "190000000596", "posicao": 26}, {"nome": "PLINIO COMTE LEITE BITTENCOURT", "numero": "23601", "votos": 37, "sq_candidato": "190000001349", "posicao": 27}, {"nome": "JUEDYR ORSAY SILVA", "numero": "44190", "votos": 33, "sq_candidato": "190000003550", "posicao": 28}, {"nome": "ARMANDO JOSE TAVARES FERREIRA", "numero": "40777", "votos": 30, "sq_candidato": "190000000737", "posicao": 29}, {"nome": "MIGUEL ALVES JEOVANI", "numero": "22555", "votos": 26, "sq_candidato": "190000004020", "posicao": 30}, {"nome": "EDSON ALBERTASSI", "numero": "15088", "votos": 22, "sq_candidato": "190000002698", "posicao": 31}, {"nome": "JOSE LEITE NADER", "numero": "22321", "votos": 22, "sq_candidato": "190000004000", "posicao": 32}, {"nome": "FELIPE DOS SANTOS PEIXOTO", "numero": "12369", "votos": 22, "sq_candidato": "190000000920", "posicao": 33}, {"nome": "DELIO CESAR LEAL", "numero": "15134", "votos": 21, "sq_candidato": "190000002696", "posicao": 34}, {"nome": "ADROALDO PEIXOTO GARANI", "numero": "22580", "votos": 20, "sq_candidato": "190000003954", "posicao": 35}, {"nome": "JOAO ALVES PEIXOTO", "numero": "27123", "votos": 18, "sq_candidato": "190000003762", "posicao": 36}, {"nome": "AURELIO GONCALVES MARQUES", "numero": "22111", "votos": 18, "sq_candidato": "190000003963", "posicao": 37}, {"nome": "MYRIAN PINTO RIOS", "numero": "12312", "votos": 17, "sq_candidato": "190000000963", "posicao": 38}, {"nome": "PAULO CESAR VASSALLO DE AZEVDO", "numero": "44015", "votos": 17, "sq_candidato": "190000003570", "posicao": 39}, {"nome": "ARISTEU RAPHAEL LIMA DA SILVEIRA", "numero": "40369", "votos": 16, "sq_candidato": "190000000735", "posicao": 40}, {"nome": "COSME JOSE SALLES", "numero": "15234", "votos": 16, "sq_candidato": "190000002693", "posicao": 41}, {"nome": "JOAO GONCALVES GARUBA", "numero": "70966", "votos": 16, "sq_candidato": "190000002303", "posicao": 42}, {"nome": "DIONISIO DE SOUZA LINS", "numero": "11111", "votos": 15, "sq_candidato": "190000000058", "posicao": 43}, {"nome": "MARIA APARECIDA CAMPOS STRAUS", "numero": "12212", "votos": 15, "sq_candidato": "190000000955", "posicao": 44}, {"nome": "JOSÉ RICARDO ARAUJO JIQUIRICA", "numero": "44200", "votos": 15, "sq_candidato": "190000003547", "posicao": 45}, {"nome": "GEORGETTE VIDOR MELLO", "numero": "23456", "votos": 14, "sq_candidato": "190000001286", "posicao": 46}, {"nome": "PAULO SERGIO RAMOS BARBOZA", "numero": "12345", "votos": 13, "sq_candidato": "190000000970", "posicao": 47}, {"nome": "ANDRÉ LUIZ LAZARONI DE MORAES", "numero": "15555", "votos": 13, "sq_candidato": "190000002684", "posicao": 48}, {"nome": "MARCOS VIEIRA BACELLAR", "numero": "70789", "votos": 12, "sq_candidato": "190000002330", "posicao": 49}, {"nome": "MARCO ANTÔNIO CASTILHO CARNEIRO", "numero": "45699", "votos": 12, "sq_candidato": "190000001318", "posicao": 50}, {"nome": "ALEXANDRE BRAZ CORREA", "numero": "10123", "votos": 11, "sq_candidato": "190000003084", "posicao": 51}, {"nome": "ROGER CARVALHO DE ALMEIDA", "numero": "65000", "votos": 11, "sq_candidato": "190000003050", "posicao": 52}, {"nome": "MARCIO PANISSET", "numero": "12617", "votos": 11, "sq_candidato": "190000000949", "posicao": 53}, {"nome": "MARCOS BEZERRA RIBEIRO SOARES", "numero": "12456", "votos": 10, "sq_candidato": "190000000951", "posicao": 54}, {"nome": "MARCUS VINICIUS DE VASCONCELOS FERREIRA", "numero": "14123", "votos": 9, "sq_candidato": "190000003799", "posicao": 55}, {"nome": "PEDRO AUGUSTO PALARETI", "numero": "15505", "votos": 7, "sq_candidato": "190000002747", "posicao": 56}, {"nome": "BERNARDO CHIM ROSSI", "numero": "15153", "votos": 7, "sq_candidato": "190000002688", "posicao": 57}, {"nome": "GILBERTO REIS DO NASCIMENTO", "numero": "20910", "votos": 7, "sq_candidato": "190000002015", "posicao": 58}, {"nome": "VITOR CESAR FERREIRA VARGAS", "numero": "25888", "votos": 7, "sq_candidato": "190000001373", "posicao": 59}, {"nome": "NILSON VIANA CESÁRIO", "numero": "13612", "votos": 6, "sq_candidato": "190000000595", "posicao": 60}, {"nome": "CARLOS ROBERTO DINAMITE DE OLIVEIRA", "numero": "15210", "votos": 6, "sq_candidato": "190000002690", "posicao": 61}, {"nome": "GUSTAVO FEIJO SAMPAIO", "numero": "22722", "votos": 6, "sq_candidato": "190000003985", "posicao": 62}, {"nome": "DAVID LOUREIRO COELHO", "numero": "22789", "votos": 6, "sq_candidato": "190000003970", "posicao": 63}, {"nome": "GENIVALDO DA SILVA CANTARINO", "numero": "27111", "votos": 6, "sq_candidato": "190000003754", "posicao": 64}, {"nome": "CLEIO GASPAR DE SA FREIRE", "numero": "36123", "votos": 6, "sq_candidato": "190000000463", "posicao": 65}, {"nome": "RAUL MARCOS PIRES GONÇALVES", "numero": "25125", "votos": 5, "sq_candidato": "190000003489", "posicao": 66}, {"nome": "CARLOS MINC BAUMFELD", "numero": "13001", "votos": 5, "sq_candidato": "190000000558", "posicao": 67}, {"nome": "ALCIONE DUARTE FERREIRA", "numero": "33033", "votos": 5, "sq_candidato": "190000000726", "posicao": 68}, {"nome": "RICARDO DOS SANTOS FIGUEIRA", "numero": "43434", "votos": 5, "sq_candidato": "190000003315", "posicao": 69}, {"nome": "AFAF FRANCIS RIBEIRO", "numero": "17000", "votos": 5, "sq_candidato": "190000003425", "posicao": 70}, {"nome": "CLARISSA BARROS ASSED MATHEUS DE OLIVEIRA", "numero": "22345", "votos": 5, "sq_candidato": "190000003967", "posicao": 71}, {"nome": "REJANE DE ALMEIDA", "numero": "65656", "votos": 5, "sq_candidato": "190000003248", "posicao": 72}, {"nome": "JAIRO SOUZA SANTOS", "numero": "20126", "votos": 5, "sq_candidato": "190000002021", "posicao": 73}, {"nome": "JOAO CARLOS SOARES GURGEL", "numero": "14190", "votos": 5, "sq_candidato": "190000003767", "posicao": 74}, {"nome": "KLEBER FERNANDES MACHADO", "numero": "13123", "votos": 5, "sq_candidato": "190000000584", "posicao": 75}, {"nome": "LUIZ PAULO CORREA DA ROCHA", "numero": "45678", "votos": 4, "sq_candidato": "190000001311", "posicao": 76}, {"nome": "RODRIGO NEVES BARRETO", "numero": "13651", "votos": 4, "sq_candidato": "190000000608", "posicao": 77}, {"nome": "DOMINGOS INÁCIO BRAZÃO", "numero": "15101", "votos": 4, "sq_candidato": "190000002697", "posicao": 78}, {"nome": "JOSÉ RENATO DE JESUS", "numero": "15107", "votos": 4, "sq_candidato": "190000002717", "posicao": 79}, {"nome": "ROBSON CAMPOS LEITE", "numero": "13013", "votos": 4, "sq_candidato": "190000000607", "posicao": 80}, {"nome": "ROSANGELA DE OLIVEIRA ZEIDAN", "numero": "13103", "votos": 4, "sq_candidato": "190000000609", "posicao": 81}, {"nome": "ANTONIO CARLOS NISHIYAMA", "numero": "11100", "votos": 4, "sq_candidato": "190000000049", "posicao": 82}, {"nome": "RONALDO DE MORAES FERREIRA", "numero": "16166", "votos": 4, "sq_candidato": "190000000645", "posicao": 83}, {"nome": "ALESSANDRO ALVES CALAZANS", "numero": "33333", "votos": 4, "sq_candidato": "190000000728", "posicao": 84}, {"nome": "EDMILSON MENEZES NASCIMENTO", "numero": "36193", "votos": 4, "sq_candidato": "190000000468", "posicao": 85}, {"nome": "JOSE ROBERTO GAMA DE OLIVEIRA", "numero": "12777", "votos": 3, "sq_candidato": "190000000941", "posicao": 86}, {"nome": "BENEDITO WILTON DE MORAIS", "numero": "40633", "votos": 3, "sq_candidato": "190000000740", "posicao": 87}, {"nome": "MELISSA POZZATO WANDERLEY", "numero": "15123", "votos": 3, "sq_candidato": "190000002735", "posicao": 88}, {"nome": "JOAO LUIS BELLOTI NACIF", "numero": "12611", "votos": 3, "sq_candidato": "190000000929", "posicao": 89}, {"nome": "KERLY GUSTAVO BEZERRA LOPES", "numero": "45123", "votos": 3, "sq_candidato": "190000001303", "posicao": 90}, {"nome": "MARCELO JOSÉ PEREIRA", "numero": "28280", "votos": 3, "sq_candidato": "190000002800", "posicao": 91}, {"nome": "MAURA DE OLIVEIRA", "numero": "22336", "votos": 3, "sq_candidato": "190000004019", "posicao": 92}, {"nome": "ANTONIO CARLOS QUESADA FERNANDES", "numero": "12334", "votos": 3, "sq_candidato": "190000000902", "posicao": 93}, {"nome": "MARCELO RODRIGUES PEREIRA", "numero": "27457", "votos": 3, "sq_candidato": "190000003793", "posicao": 94}, {"nome": "PAULO RICARDO GONCALVES RAUNHEITTI", "numero": "14111", "votos": 3, "sq_candidato": "190000003814", "posicao": 95}, {"nome": "RONALD FARIA CRESPO", "numero": "27277", "votos": 2, "sq_candidato": "190000003824", "posicao": 96}, {"nome": "AGUILAR RIBEIRO DA SILVA", "numero": "65321", "votos": 2, "sq_candidato": "190000001847", "posicao": 97}, {"nome": "WILSON RODRIGUES CABRAL FILHO", "numero": "40140", "votos": 2, "sq_candidato": "190000000825", "posicao": 98}, {"nome": "BRUNO BARBOSA CORREIA", "numero": "12000", "votos": 2, "sq_candidato": "190000000904", "posicao": 99}, {"nome": "ODETE PEREIRA DA ROCHA DUARTE", "numero": "65165", "votos": 2, "sq_candidato": "190000003072", "posicao": 100}, {"nome": "PAULO CESAR GENASIO DE SOUZA", "numero": "43190", "votos": 2, "sq_candidato": "190000003372", "posicao": 101}, {"nome": "MARLENE ROCHA E SILVA", "numero": "23369", "votos": 2, "sq_candidato": "190000001329", "posicao": 102}, {"nome": "ROGÉRIO BITTAR", "numero": "40123", "votos": 2, "sq_candidato": "190000000816", "posicao": 103}, {"nome": "LEONARDO SOARES GIORDANO", "numero": "13130", "votos": 2, "sq_candidato": "190000000586", "posicao": 104}, {"nome": "ANDRÉ JOSÉ DA CRUZ", "numero": "13122", "votos": 2, "sq_candidato": "190000000551", "posicao": 105}, {"nome": "ATILA NUNES PEREIRA FILHO", "numero": "17172", "votos": 2, "sq_candidato": "190000003292", "posicao": 106}, {"nome": "GERALDO CAETANO", "numero": "22222", "votos": 2, "sq_candidato": "190000003982", "posicao": 107}, {"nome": "ALBERTO LOPES CANTALICE", "numero": "13667", "votos": 2, "sq_candidato": "190000000549", "posicao": 108}, {"nome": "PAULO DE HERACLITO LIMA FILHO", "numero": "11000", "votos": 2, "sq_candidato": "190000000109", "posicao": 109}, {"nome": "ROBERTO DO NASCIMENTO CID", "numero": "12333", "votos": 2, "sq_candidato": "190000000973", "posicao": 110}, {"nome": "WALDYR ALVES DE OLIVEIRA", "numero": "70636", "votos": 2, "sq_candidato": "190000002357", "posicao": 111}, {"nome": "MANOEL ANGELO RUGERO", "numero": "25244", "votos": 2, "sq_candidato": "190000001312", "posicao": 112}, {"nome": "FABIO FRANCISCO DA SILVA", "numero": "22300", "votos": 2, "sq_candidato": "190000003978", "posicao": 113}, {"nome": "RODRIGO CARVALHO RIBEIRO DANTAS", "numero": "25123", "votos": 2, "sq_candidato": "190000001360", "posicao": 114}, {"nome": "ELIEZER DE ALBUQUERQUE PEREIRA", "numero": "31234", "votos": 1, "sq_candidato": "190000001560", "posicao": 115}, {"nome": "MARCELO RUBENS VIEIRA VERAS", "numero": "12512", "votos": 1, "sq_candidato": "190000000948", "posicao": 116}, {"nome": "MARIA ESTER SILVA MENDONÇA", "numero": "50050", "votos": 1, "sq_candidato": "190000003664", "posicao": 117}, {"nome": "ROGERIO AUGUSTO LEITAO", "numero": "11223", "votos": 1, "sq_candidato": "190000000114", "posicao": 118}, {"nome": "ROBERTO PETTO GOMES", "numero": "15456", "votos": 1, "sq_candidato": "190000002752", "posicao": 119}, {"nome": "JANIO DOS SANTOS MENDES", "numero": "12601", "votos": 1, "sq_candidato": "190000000924", "posicao": 120}, {"nome": "FRANZ FORTES THALHOFER", "numero": "44400", "votos": 1, "sq_candidato": "190000003532", "posicao": 121}, {"nome": "JOÃO FERREIRA NETO", "numero": "33321", "votos": 1, "sq_candidato": "190000000778", "posicao": 122}, {"nome": "RAFAEL ALOISIO FREITAS", "numero": "11123", "votos": 1, "sq_candidato": "190000000112", "posicao": 123}, {"nome": "ROOSEVELT BRASIL FONSECA", "numero": "15015", "votos": 1, "sq_candidato": "190000002753", "posicao": 124}, {"nome": "JACKSON ANCHIETA DE OLIVEIRA", "numero": "28281", "votos": 1, "sq_candidato": "190000002780", "posicao": 125}, {"nome": "RICARDO MARTINS DAVID", "numero": "12198", "votos": 1, "sq_candidato": "190000000972", "posicao": 126}, {"nome": "CARLOS ALBERTO DOS SANTOS", "numero": "11222", "votos": 1, "sq_candidato": "190000000055", "posicao": 127}, {"nome": "FLÁVIO NAKANDAKARE DE OLIVEIRA", "numero": "13631", "votos": 1, "sq_candidato": "190000000573", "posicao": 128}, {"nome": "JORGE FERREIRA CAMPOS", "numero": "28624", "votos": 1, "sq_candidato": "190000003408", "posicao": 129}, {"nome": "RUBENS JOSÉ FRANÇA BOMTEMPO", "numero": "40789", "votos": 1, "sq_candidato": "190000000820", "posicao": 130}, {"nome": "ANTONIO CHARBEL JOSE ZAIB", "numero": "12001", "votos": 1, "sq_candidato": "190000000903", "posicao": 131}, {"nome": "ANTONIO MARCOS DA SILVA", "numero": "11200", "votos": 1, "sq_candidato": "190000000051", "posicao": 132}, {"nome": "ROBSON DOS SANTOS FRANCA", "numero": "25111", "votos": 1, "sq_candidato": "190000003697", "posicao": 133}, {"nome": "CARLOS EDUARDO FAYAL DE LYRA", "numero": "40111", "votos": 1, "sq_candidato": "190000000744", "posicao": 134}, {"nome": "FERNANDO OTAVIO GOMES DA SILVEIRA", "numero": "11023", "votos": 1, "sq_candidato": "190000000068", "posicao": 135}, {"nome": "ROSENVERG REIS DE OLIVEIRA", "numero": "15126", "votos": 1, "sq_candidato": "190000002754", "posicao": 136}, {"nome": "MARCELINO D ALMEIDA", "numero": "15369", "votos": 1, "sq_candidato": "190000002726", "posicao": 137}, {"nome": "NAYMARA COSTA MAIA", "numero": "12378", "votos": 1, "sq_candidato": "190000000964", "posicao": 138}, {"nome": "REINALDO PEREIRA PINTO", "numero": "22223", "votos": 1, "sq_candidato": "190000004032", "posicao": 139}, {"nome": "RUBENS ANTONIO ANDRADE COSTA", "numero": "40603", "votos": 1, "sq_candidato": "190000000819", "posicao": 140}, {"nome": "GRACIETE SANTANA NOGUEIRA NUNES", "numero": "21123", "votos": 1, "sq_candidato": "190000001663", "posicao": 141}, {"nome": "HENRIQUE SANTANA AZEREDO", "numero": "25369", "votos": 1, "sq_candidato": "190000001291", "posicao": 142}, {"nome": "WALTER NOBRE GOMES", "numero": "25333", "votos": 1, "sq_candidato": "190000001374", "posicao": 143}, {"nome": "MARLON VIVAS CABRAL", "numero": "20123", "votos": 1, "sq_candidato": "190000002060", "posicao": 144}, {"nome": "NELSON REIS CONCEIÇÃO", "numero": "33133", "votos": 1, "sq_candidato": "190000000802", "posicao": 145}, {"nome": "FLÁVIO DOS SANTOS NOGUEIRA", "numero": "40010", "votos": 1, "sq_candidato": "190000000759", "posicao": 146}, {"nome": "FRANCISCO MANOEL DE CARVALHO", "numero": "15345", "votos": 1, "sq_candidato": "190000002704", "posicao": 147}, {"nome": "ALCIR VIEIRA", "numero": "70010", "votos": 1, "sq_candidato": "190000002261", "posicao": 148}, {"nome": "BENEDITO VITOR JUNIOR", "numero": "10010", "votos": 1, "sq_candidato": "190000003087", "posicao": 149}, {"nome": "CARMEN LUCIA DE OLIVEIRA GAMA", "numero": "43743", "votos": 1, "sq_candidato": "190000004307", "posicao": 150}, {"nome": "CESAR AUGUSTO DOS SANTOS", "numero": "23193", "votos": 1, "sq_candidato": "190000001260", "posicao": 151}, {"nome": "CONCEIÇÃO APARECIDA CASSANO TORRES", "numero": "15888", "votos": 1, "sq_candidato": "190000002692", "posicao": 152}, {"nome": "ZAQUEU DA SILVA TEIXEIRA", "numero": "13333", "votos": 1, "sq_candidato": "190000000623", "posicao": 153}, {"nome": "GILBERTO SILVA PALMARES", "numero": "13455", "votos": 1, "sq_candidato": "190000000574", "posicao": 154}, {"nome": "MARINETE XAVIER DE FREITAS", "numero": "40801", "votos": 1, "sq_candidato": "190000000796", "posicao": 155}, {"nome": "MARIO DA CRUZ SENNA FILHO", "numero": "20333", "votos": 1, "sq_candidato": "190000002056", "posicao": 156}, {"nome": "ANDRÉ LUIZ CECILIANO", "numero": "13567", "votos": 1, "sq_candidato": "190000000552", "posicao": 157}, {"nome": "JANE CHRISTINE DIAS ANDRADE FIGUEIRA", "numero": "15151", "votos": 1, "sq_candidato": "190000002708", "posicao": 158}, {"nome": "PAULO IZECKSOHN", "numero": "70899", "votos": 1, "sq_candidato": "190000002342", "posicao": 159}, {"nome": "ANTONIO CARLOS DA SILVA PIRES", "numero": "22220", "votos": 1, "sq_candidato": "190000003960", "posicao": 160}, {"nome": "CARLOS ROBERTO PAIVA", "numero": "13100", "votos": 1, "sq_candidato": "190000000561", "posicao": 161}, {"nome": "DANIEL LIMA LINDOSO", "numero": "31323", "votos": 1, "sq_candidato": "190000001548", "posicao": 162}, {"nome": "DJANIRA DOLORES MONTENEGRO", "numero": "43800", "votos": 1, "sq_candidato": "190000003297", "posicao": 163}, {"nome": "ANTONIO ROSALVO PAZ DE VASCONCELOS TORRES", "numero": "25321", "votos": 1, "sq_candidato": "190000001252", "posicao": 164}, {"nome": "JOACAZES LORES DA SILVA", "numero": "40234", "votos": 1, "sq_candidato": "190000000769", "posicao": 165}, {"nome": "ALEXANDRE ROBERTO LEITE", "numero": "11112", "votos": 1, "sq_candidato": "190000000040", "posicao": 166}, {"nome": "LUIZ FELIPE PAULINO AUNI", "numero": "22233", "votos": 1, "sq_candidato": "190000004011", "posicao": 167}, {"nome": "SADINOEL OLIVEIRA GOMES SOUZA", "numero": "22133", "votos": 1, "sq_candidato": "190000004039", "posicao": 168}, {"nome": "NOEL DE CARVALHO NETO", "numero": "15280", "votos": 1, "sq_candidato": "190000002742", "posicao": 169}, {"nome": "RALEIGH RAMALHO", "numero": "14014", "votos": 1, "sq_candidato": "190000003819", "posicao": 170}, {"nome": "ULISSES MARTINS", "numero": "22213", "votos": 1, "sq_candidato": "190000004051", "posicao": 171}, {"nome": "LUIZ FERNANDO FELIPPE GUIDA", "numero": "43456", "votos": 1, "sq_candidato": "190000002811", "posicao": 172}, {"nome": "EVERALDO EUFRASIO FRANCISCO", "numero": "22400", "votos": 1, "sq_candidato": "190000003977", "posicao": 173}, {"nome": "FLAVIO NANTES BOLSONARO", "numero": "11120", "votos": 1, "sq_candidato": "190000000070", "posicao": 174}, {"nome": "GOTHARDO LOPES NETTO", "numero": "40202", "votos": 1, "sq_candidato": "190000000762", "posicao": 175}, {"nome": "RICARDO DOUGLAS VALADARES", "numero": "44233", "votos": 1, "sq_candidato": "190000003571", "posicao": 176}], "BAIRROS": {}}}}}